[
  {
    "tags": {},
    "filePath": "/Users/yingyingchang/Downloads/ant-design-4.24.10/components/auto-complete/index.tsx",
    "description": "自动完成",
    "displayName": "AutoComplete",
    "methods": [],
    "props": {
      "style": {
        "defaultValue": "",
        "description": "自定义样式",
        "name": "style",
        "required": false,
        "type": {
          "name": "CSSProperties"
        }
      },
      "options": {
        "defaultValue": null,
        "description": "下拉选项",
        "needMock": true,
        "name": "options",
        "required": false,
        "expandPanel": true,
        "type": {
          "name": "array",
          "item": {
            "label": {
              "description": "文本",
              "expandPanel": true,
              "name": "label",
              "type": {
                "name": "string"
              }
            },
            "value": {
              "description": "",
              "name": "value",
              "type": {
                "name": "Key"
              }
            }
          }
        }
      },
      "value": {
        "defaultValue": "",
        "description": "选中项",
        "expandPanel": true,
        "name": "value",
        "required": false,
        "type": {
          "name": "string"
        }
      },
      "defaultValue": {
        "defaultValue": "",
        "description": "默认选中项",
        "expandPanel": true,
        "name": "defaultValue",
        "required": false,
        "type": {
          "name": "string"
        }
      },
      "disabled": {
        "defaultValue": false,
        "description": "禁用",
        "expandPanel": true,
        "name": "disabled",
        "required": false,
        "type": {
          "name": "boolean"
        }
      },
      "open": {
        "defaultValue": false,
        "description": "展开下拉菜单",
        "expandPanel": true,
        "name": "open",
        "required": false,
        "type": {
          "name": "boolean"
        }
      },
      "placeholder": {
        "defaultValue": "",
        "description": "输入框提示文字",
        "expandPanel": true,
        "name": "placeholder",
        "required": false,
        "type": {
          "name": "string"
        }
      },
      "allowClear": {
        "defaultValue": false,
        "description": "是否添加清除图标",
        "expandPanel": true,
        "name": "allowClear",
        "required": false,
        "type": {
          "name": "boolean"
        }
      },
      "autoFocus": {
        "defaultValue": false,
        "description": "是否默认聚焦",
        "name": "autoFocus",
        "required": false,
        "type": {
          "name": "boolean"
        }
      },
      "backfill": {
        "defaultValue": false,
        "description": "开启键盘选择",
        "tips": "使用键盘选择选项的时候把选中项回填到输入框中",
        "name": "backfill",
        "required": false,
        "type": {
          "name": "boolean"
        }
      },
      "status": {
        "defaultValue": "",
        "description": "输入框状态",
        "name": "status",
        "required": false,
        "type": {
          "name": "choice",
          "enum": ["success", "error", "warning", "validating"]
        }
      },
      "dropdownMatchSelectWidth": {
        "defaultValue": true,
        "description": "下拉菜单和选择器同宽",
        "tips": "默认将设置 min-width，当值小于选择框宽度时会被忽略。false 时会关闭虚拟滚动",
        "name": "dropdownMatchSelectWidth",
        "required": false,
        "type": {
          "name": "boolean"
        }
      },
      "defaultActiveFirstOption": {
        "defaultValue": true,
        "description": "是否默认高亮第一个选项。",
        "name": "defaultActiveFirstOption",
        "required": false,
        "type": {
          "name": "boolean"
        }
      },
      "defaultOpen": {
        "defaultValue": false,
        "description": "是否默认展开下拉菜单",
        "name": "defaultOpen",
        "required": false,
        "type": {
          "name": "boolean"
        }
      }
    }
  }
]